{"id":"14662","shelfmark":"ENA NS 85.1314","multifragment":"","type_en":"List or table","type_he":"רשימה או טבלה","lang_en":"Judaeo-Arabic","lang_he":"יהודית-ערבית","lang2_en":"","lang2_he":"","lang_note":"","origin":"","destination":"","region":"","date":"","date_original":"","date_standard":"","date_inferred":"","date_rationale":"","library":"בית המדרש לרבנים","library_raw":"JTS","collection":"JTS","description":"Distribution list in the hand of Ḥalfon b. Menashshe. Mentions: Fuhayd; baʿal ḥalom (a dream interpreter); Abū l-Ḥasan al-Parnas; Maʿālī b. Ghazāl; the daughter of [...]. Some of the same people, including the dream interpreter, appear in T-S NS 226.105 (PGPID 24246).","tags":[],"has_transcription":false,"has_translation":false,"iiif_urls":["https://figgy.princeton.edu/concern/scanned_resources/ad293ebb-9831-4c01-9c11-ba0cafa1d95c/manifest"],"fragment_urls":[],"princeton_url":"https://geniza.princeton.edu/documents/14662/","mentioned":"","description_he":"רשימת חלוקה ביד חלפון ב' מנשה. מזכיר: פוחיד; בעל חלום (פותר חלומות); אבו אל-חסן הפרנס; מעאלי ב' גזאל; בת ה[...]. חלק מאותם אנשים, כולל פותר החלומות, מופיעים ב-T-S NS 226.105 (PGPID 24246).","prev":"14661","next":"14663","pos":10365,"total":35924}