{"id":"15837","shelfmark":"MS R1911","multifragment":"","type_en":"Legal query or responsum","type_he":"שאלה משפטית","lang_en":"Hebrew","lang_he":"עברית","lang2_en":"","lang2_he":"","lang_note":"","origin":"","destination":"","region":"","date":"","date_original":"","date_standard":"","date_inferred":"","date_rationale":"","library":"בית המדרש לרבנים","library_raw":"JTS","collection":"JTS","description":"See MS R1911, fol. 1 (PGPID 15838)","tags":["responsa"],"has_transcription":false,"has_translation":false,"iiif_urls":[],"fragment_urls":[],"princeton_url":"https://geniza.princeton.edu/documents/15837/","mentioned":"","description_he":"ראה MS R1911, דף 1 (PGPID 15838).","tags_he":["עברית"],"prev":"15836","next":"15838","pos":21947,"total":35924}