{"id":"16224","shelfmark":"T-S 8J7.12","multifragment":"","type_en":"Legal document","type_he":"מסמך משפטי","lang_en":"Aramaic, Hebrew, Judaeo-Arabic","lang_he":"Aramaic, Hebrew, Judaeo-Arabic","lang2_en":"","lang2_he":"","lang_note":"","origin":"","destination":"","region":"","date":"1100–1138","date_original":"","date_standard":"","date_inferred":"1100–1138","date_rationale":"Paleography","library":"ספריית קיימברידג'","library_raw":"CUL","collection":"CUL, T-S","description":"Legal document in the hand of Ḥalfon b. Menashshe ha-Levi (1100–38 CE). Fragment (upper part only). In which Abū Saʿd al-Ḥarīrī Ḥalfon b. Yiṣḥaq, the brother of Abū l-Ḥasan Daniʾel, acknowledges something (perhaps a debt) for Hiba b. Avraham. There is also a filing note on verso (\"document from Abū Saʿd al-Ḥarīrī to Hiba\"). (Information in part from CUDL)","tags":[],"has_transcription":false,"has_translation":false,"iiif_urls":["https://cudl.lib.cam.ac.uk/iiif/MS-TS-00008-J-00007-00012"],"fragment_urls":["https://cudl.lib.cam.ac.uk/view/MS-TS-00008-J-00007-00012"],"princeton_url":"https://geniza.princeton.edu/documents/16224/","mentioned":"","description_he":"מסמך משפטי בכתב ידו של חלפון בן מנשה הלוי (1100-1138 לספירה). שבר (רק החלק העליון). שבו אבו סעד אל-חרירי חלפון בן יצחק, אחיו של אבו אל-חסן דניאל, מודה במשהו (אולי חוב) עבור הבה בן אברהם. יש גם הערת תיוק בצד ב' ('מסמך מאבו סעד אל-חרירי לְהִבָּה'). (מידע חלקית מתוך CUDL)","prev":"16223","next":"16225","pos":11754,"total":35924}