{"id":"17062","shelfmark":"T-S 16.46","multifragment":"","type_en":"Letter","type_he":"מכתב","lang_en":"Hebrew","lang_he":"עברית","lang2_en":"","lang2_he":"","lang_note":"Hebrew (isolated Tiberian vocalisation)","origin":"","destination":"","region":"","date":"1420","date_original":"","date_standard":"","date_inferred":"1420","date_rationale":"Other (please specify)","library":"ספריית קיימברידג'","library_raw":"CUL","collection":"CUL, T-S","description":"Letter written by [Joseph b.] Elʿazar in Palestine, mentioning various individuals including Abū l-Faraji, Elʿazar the doctor, Joseph the doctor, ʿAbd al-Karam, Sulayman b. ʿAbd al-ʿAziz, and David the Spaniard. The letter also refers to the house of Shemuʾel the prophet. Dated using the phrase ולקחתי אתכם לי לעם, of which the last word is dotted. This equates to 140, i.e. 5140 (= 1380 CE). Assaf (1944:190), however, suggests לי should also be dotted, giving a date 1420 CE. (Information from CUDL)","tags":["15th c"],"has_transcription":false,"has_translation":false,"iiif_urls":["https://cudl.lib.cam.ac.uk/iiif/MS-TS-00016-00046"],"fragment_urls":["https://cudl.lib.cam.ac.uk/view/MS-TS-00016-00046"],"princeton_url":"https://geniza.princeton.edu/documents/17062/","mentioned":"","description_he":"מכתב בעברית מהמאה ה-15. מוחזק בספריית קיימברידג'.","prev":"17061","next":"17063","pos":12454,"total":35924}