{"id":"20076","shelfmark":"T-S 12.779","multifragment":"","type_en":"Legal document","type_he":"מסמך משפטי","lang_en":"Aramaic, Hebrew, Judaeo-Arabic","lang_he":"Aramaic, Hebrew, Judaeo-Arabic","lang2_en":"","lang2_he":"","lang_note":"","origin":"","destination":"","region":"","date":"1096-04-28","date_original":"Monday, 3 Iyyar 1407","date_standard":"1096-04-28","date_inferred":"","date_rationale":"","library":"ספריית קיימברידג'","library_raw":"CUL","collection":"CUL, T-S","description":"Faded legal document in the hand of Hillel b. ʿEli. Location: Fustat. Dated: Monday, 3 Iyyar 1407 Seleucid = 28 April 1096 CE. Parties: Meshullam b. Shelomo Ibn Sunaynāt al-Muqaddasī (appears also in T-S AS 156.138 + T-S 10J8.4 + T-S 6J3.12 (PGPID 3069)) who serves as a representative of a young women regarding a legal document written in Muslim court. Also mentions Berakhot and Yehuda ha-Rav ha-Muvhaq (יהודה הרב המובהק) who might be Yehuda b. Yosef. AA/ASE","tags":["Hillel b. 'Eli"],"has_transcription":false,"has_translation":false,"iiif_urls":["https://cudl.lib.cam.ac.uk//iiif/MS-TS-00012-00779"],"fragment_urls":[],"princeton_url":"https://geniza.princeton.edu/documents/20076/","mentioned":"","description_he":"מסמך משפטי דהוי בכתב ידו של הלל בן עלי; מקום: פסטאט; תאריך: יום שני, ג' אייר 1407 לשטרות = 28 באפריל 1096 לספירה; משולם בן שלמה אבן סונינאת משמש נציג לאישה צעירה","prev":"20073","next":"20084","pos":14625,"total":35924}