{"id":"20824","shelfmark":"T-S Ar.39.222","multifragment":"","type_en":"Letter","type_he":"מכתב","lang_en":"Arabic","lang_he":"ערבית","lang2_en":"","lang2_he":"","lang_note":"","origin":"","destination":"","region":"","date":"","date_original":"","date_standard":"","date_inferred":"","date_rationale":"","library":"ספריית קיימברידג'","library_raw":"CUL","collection":"CUL, T-S","description":"Letter/report, concerning a legal matter regarding occupancy/tenancy (sakn). The beginnings of five lines are preserved. Mentions someone named Ibrāhīm b. Maḥbūb al-Muhandis in l. 3, a witness, and money (ʿayn). Needs further examination.","tags":["DIMME"],"has_transcription":false,"has_translation":false,"iiif_urls":[],"fragment_urls":[],"princeton_url":"https://geniza.princeton.edu/documents/20824/","mentioned":"","description_he":"מכתב/דוח הנוגע לענין משפטי בדבר אכסון/דיירות. שמורות תחיליות של חמש שורות. מוזכרים אברהים בן מחבוב אל-מוהנדס, עד וכסף. דורש בדיקה נוספת.","prev":"20823","next":"20825","pos":23109,"total":35924}