{"id":"22503","shelfmark":"T-S AS 170.36","multifragment":"","type_en":"Letter","type_he":"מכתב","lang_en":"Judaeo-Arabic","lang_he":"יהודית-ערבית","lang2_en":"","lang2_he":"","lang_note":"","origin":"","destination":"","region":"","date":"","date_original":"","date_standard":"","date_inferred":"","date_rationale":"","library":"ספריית קיימברידג'","library_raw":"CUL","collection":"CUL, T-S","description":"Note probably from one judge or court clerk to another. In Judaeo-Arabic. “I have checked everything with me, even the house of the rayyis. It must be with you. If not, we’ll write a new one. But check with you. And peace.” (Presumably referring to a legal deed or court record.) Written on verso of an Arabic document.","tags":[],"has_transcription":false,"has_translation":false,"iiif_urls":[],"fragment_urls":[],"princeton_url":"https://geniza.princeton.edu/documents/22503/","mentioned":"","description_he":"פתק כנראה משופט אחד או פקיד בית דין לאחר. ביהודית-ערבית. 'בדקתי כל מה שאצלי, אפילו בית הראיס. חייב להיות אצלך. אם לא — נכתוב חדש. אבל בדוק אצלך. ושלום.' (כנראה מתייחס לשטר משפטי.) נכתב על גב מסמך ערבי.","prev":"22502","next":"22505","pos":24231,"total":35924}