{"id":"22946","shelfmark":"T-S AS 223.229","multifragment":"","type_en":"Legal document","type_he":"מסמך משפטי","lang_en":"Aramaic","lang_he":"ארמית","lang2_en":"","lang2_he":"","lang_note":"","origin":"","destination":"","region":"","date":"","date_original":"","date_standard":"","date_inferred":"","date_rationale":"","library":"ספריית קיימברידג'","library_raw":"CUL","collection":"CUL, T-S","description":"Minute fragment, very faded, from the top of a legal deed dated according to the Creation, but no date is preserved. A groom is mentioned in line 3 yet the relevant name is not preserved.","tags":[],"has_transcription":false,"has_translation":false,"iiif_urls":[],"fragment_urls":[],"princeton_url":"https://geniza.princeton.edu/documents/22946/","mentioned":"","description_he":"שרידים זעירים ודהויים מאוד מראש שטר משפטי מתוארך לפי בריאת העולם, אך התאריך לא נשמר. חתן מוזכר בשורה 3 אך שמו לא נשתמר.","tags_he":["מסמך משפטי","ארמית"],"prev":"22945","next":"22948","pos":24566,"total":35924}