{"id":"23292","shelfmark":"T-S Misc.11.76","multifragment":"","type_en":"List or table","type_he":"רשימה או טבלה","lang_en":"Judaeo-Arabic","lang_he":"יהודית-ערבית","lang2_en":"","lang2_he":"","lang_note":"","origin":"","destination":"","region":"","date":"","date_original":"","date_standard":"","date_inferred":"","date_rationale":"","library":"ספריית קיימברידג'","library_raw":"CUL","collection":"CUL, T-S","description":"Judaeo-Arabic fragment in very rudimentary handwriting, naming sums of money held by various people (Dawud has 5.5 dinars, al-Shaykh Abū [...] has 1.75 dinars. . .). Likely 19th-century, since the first line says, \"al-qiṭāra alladhī (!) dakhalat ilā l-Minya,\" and what would this mean if not a train?","tags":["19th c, train"],"has_transcription":false,"has_translation":false,"iiif_urls":[],"fragment_urls":[],"princeton_url":"https://geniza.princeton.edu/documents/23292/","mentioned":"","description_he":"קטע ערבית-יהודית בכתב יד ראשוני, המציין סכומי כסף אצל אנשים שונים. ככל הנראה מהמאה ה-19, שכן השורה הראשונה מזכירה \"אל-קיטארה\" שנכנסה אל-מנייא — ומה פירוש הדבר אם לא רכבת?","tags_he":["חשבונות","יהודית-ערבית"],"prev":"23291","next":"23293","pos":24807,"total":35924}