{"id":"23329","shelfmark":"T-S Misc.22.69","multifragment":"","type_en":"Letter","type_he":"מכתב","lang_en":"Arabic","lang_he":"ערבית","lang2_en":"","lang2_he":"","lang_note":"","origin":"","destination":"","region":"","date":"","date_original":"","date_standard":"","date_inferred":"","date_rationale":"","library":"ספריית קיימברידג'","library_raw":"CUL","collection":"CUL, T-S","description":"Fragment of a document or letter in Arabic script. Refers to \"the ladies\" (al-sādāt), Abū Yaʿqūb Ibn al-Baradānī, and an upper storey (al-ṭabaqa al-ʿāliya). Needs examination.\n\nOn verso there is piyyuṭ in Hebrew in the hand of a familiar scribe (see e.g. T-S AS 132.204 (PGPID 29232)).","tags":[],"has_transcription":false,"has_translation":false,"iiif_urls":[],"fragment_urls":[],"princeton_url":"https://geniza.princeton.edu/documents/23329/","mentioned":"","description_he":"מכתב בערבית. מוחזק בספריית קיימברידג'.","prev":"23327","next":"23330","pos":24838,"total":35924}