{"id":"25693","shelfmark":"T-S NS 324.41","multifragment":"","type_en":"Letter","type_he":"מכתב","lang_en":"Hebrew","lang_he":"עברית","lang2_en":"","lang2_he":"","lang_note":"","origin":"","destination":"","region":"","date":"","date_original":"","date_standard":"","date_inferred":"","date_rationale":"","library":"ספריית קיימברידג'","library_raw":"CUL","collection":"CUL, T-S","description":"Letter from Elʿazar b. Yaʾir the cantor to his teacher Aharon b. [...]. In Hebrew. Consisting almost entirely of blessings; possibly requesting charity or assistance. AA/ASE","tags":[],"has_transcription":false,"has_translation":false,"iiif_urls":[],"fragment_urls":[],"princeton_url":"https://geniza.princeton.edu/documents/25693/","mentioned":"","description_he":"מכתב מאלעזר בן יאיר החזן לרבו אהרן בן [...]. בעברית. מורכב כמעט כולו מברכות; ייתכן שמבקש צדקה או סיוע. AA/ASE","tags_he":["מכתב","עברית","צדקה"],"prev":"25692","next":"25694","pos":26562,"total":35924}