{"id":"27795","shelfmark":"Yevr. II K 52","multifragment":"","type_en":"Legal document","type_he":"מסמך משפטי","lang_en":"Hebrew","lang_he":"עברית","lang2_en":"","lang2_he":"","lang_note":"","origin":"","destination":"","region":"","date":"1797-02-14","date_original":"Wednesday 18 Shevat 5557","date_standard":"1797-02-14","date_inferred":"","date_rationale":"","library":"הספרייה הלאומית רוסיה","library_raw":"NLR","collection":"NLR","description":"Decorated Karaite ketubba from Cairo. Dated: 18 Shevat 5557 AM (February 1797 CE). The groom is Nissim b. Avraham and the bride is Esther d. Elisha the cantor.","tags":["karaite ketubba, Karaite"],"has_transcription":false,"has_translation":false,"iiif_urls":[],"fragment_urls":[],"princeton_url":"https://geniza.princeton.edu/documents/27795/","mentioned":"","description_he":"מסמך משפטי בעברית. מוחזק בהספרייה הלאומית רוסיה.","prev":"27794","next":"27796","pos":28077,"total":35924}