{"id":"27902","shelfmark":"Yevr.-Arab. II 1163","multifragment":"","type_en":"Literary text","type_he":"טקסט ספרותי","lang_en":"Hebrew, Judaeo-Arabic","lang_he":"Hebrew, Judaeo-Arabic","lang2_en":"","lang2_he":"","lang_note":"","origin":"","destination":"","region":"","date":"","date_original":"","date_standard":"","date_inferred":"","date_rationale":"","library":"הספרייה הלאומית רוסיה","library_raw":"NLR","collection":"NLR","description":"Literary. Muqaddimāt and tafsīr.","tags":[],"has_transcription":false,"has_translation":false,"iiif_urls":[],"fragment_urls":[],"princeton_url":"https://geniza.princeton.edu/documents/27902/","mentioned":"","description_he":"טקסט ספרותי בHebrew, Judaeo-Arabic. מוחזק בהספרייה הלאומית רוסיה.","prev":"27901","next":"27903","pos":28180,"total":35924}