{"id":"28078","shelfmark":"Yevr.-Arab. II 1739 + Yevr.-Arab. II 1408","multifragment":"","type_en":"Letter","type_he":"מכתב","lang_en":"Judaeo-Arabic","lang_he":"יהודית-ערבית","lang2_en":"","lang2_he":"","lang_note":"","origin":"","destination":"","region":"","date":"","date_original":"","date_standard":"","date_inferred":"","date_rationale":"","library":"הספרייה הלאומית רוסיה · הספרייה הלאומית רוסיה","library_raw":"NLR ; NLR","collection":"NLR ; NLR","description":"Letter draft in Judaeo-Arabic. Perhaps intended to be sent from Fustat/Cairo to Jerusalem. Dating: Unknown, catalogued as 18th century. The writer reports on the money that was with the addressee's brother (? karīmak) Yaʿaqov Ḥazzan and his maternal uncle Yehuda Rofe. He recounts how the addressee traveled to Jerusalem, then to Istanbul and \"the lands above it,\" then Damascus where he married, then Jerusalem. Also mentions the Dār Simḥa synagogue in Cairo.","tags":["Damascus, Istanbul"],"has_transcription":false,"has_translation":false,"iiif_urls":[],"fragment_urls":[],"princeton_url":"https://geniza.princeton.edu/documents/28078/","mentioned":"Constantinople, Damascus, Jerusalem","description_he":"טיוטת מכתב ביהודית-ערבית, אולי מפוסטאט/קהיר לירושלים. תיארוך: ממוין כמאה ה-18. הכותב מדווח על כסף שהיה עם יעקב חזן ויהודה רופא, ומספר על מסע הנמען לירושלים, איסטנבול, דמשק ובחזרה. מזכיר את דאר שמחה.","tags_he":["מכתב","יהודית-ערבית","רפואה","פוסטאט","קהיר","ירושלים","דמשק","חזן"],"prev":"28077","next":"28079","pos":28351,"total":35924}