{"id":"2833","shelfmark":"T-S 10J13.21","multifragment":"","type_en":"Letter","type_he":"מכתב","lang_en":"Judaeo-Arabic","lang_he":"יהודית-ערבית","lang2_en":"Arabic","lang2_he":"ערבית","lang_note":"","origin":"","destination":"Tyre","region":"","date":"","date_original":"","date_standard":"","date_inferred":"","date_rationale":"","library":"ספריית קיימברידג'","library_raw":"CUL","collection":"CUL, T-S","description":"Letter from Yaḥyā b. Saʿāda the physician (al-ṭabīb), in Ashqelon, to Abū Naṣr Yehuda b. Mūsā al-Dimashqi, in Tyre. Informing him about payments he had made and regretting that he could not do much for Abū l-Faḍl, whom Yehuda had sent to him. Yehuda's shipments were being withheld by claims of a third party, Abū l-Ṭayyib Mukhtār b. Ṣadaqa. Yehuda is urged to come quickly \"before the travel of the ships to the west.\" (Information mainly from Mediterranean Society, I, p. 268, and Goitein's index cards)","tags":["Tyre, Ashqelon"],"has_transcription":false,"has_translation":false,"iiif_urls":["https://cudl.lib.cam.ac.uk/iiif/MS-TS-00010-J-00013-00021"],"fragment_urls":["https://cudl.lib.cam.ac.uk/view/MS-TS-00010-J-00013-00021/1"],"princeton_url":"https://geniza.princeton.edu/documents/2833/","mentioned":"","description_he":"מכתב מיחיא ב' סעאדה הרופא, באשקלון, לאבו נצר יהודה ב' מוסא אל-דמשקי, בצור. מדווח על תשלומים ששילם ועל אי-יכולתו לסייע לאבו אל-פדל. משלוחי יהודה עוכבו בתביעות צד שלישי. יהודה מתבקש לבוא מהר 'לפני יציאת הספינות מערבה'.","tags_he":["מכתב","יהודית-ערבית","רפואה","דמשק","צור"],"prev":"2832","next":"2834","pos":1885,"total":35924}