{"id":"28975","shelfmark":"Stras. 4068/30","multifragment":"","type_en":"List or table","type_he":"רשימה או טבלה","lang_en":"Hebrew","lang_he":"עברית","lang2_en":"","lang2_he":"","lang_note":"","origin":"","destination":"","region":"","date":"","date_original":"","date_standard":"","date_inferred":"","date_rationale":"","library":"BNUS","library_raw":"BNUS","collection":"BNUS","description":"Descriptions of the contents of a collection of books in two different hands: the first, neater block names Yehudah b. Yahya and the text of the Tāj and Bereshit Rabbah and the Torah and the 5 Megillot and Baer Heitev and the Gemara of Hullin and the laws of Shehitah. The second block in rudimentary handwriting is harder to read. It names 'Ayn Ya'aqov, Pesikta ha-Nasi ha-Gadol, Humash ha-Gadol, and Rav Alfas, and \"three excerpts of the Rambam.\" He signs \"I am Men[ah?]em b. Yehudah al-Mujhid (?).\" Probably late, at least 16th century. ASE.","tags":["book trade, Late"],"has_transcription":false,"has_translation":false,"iiif_urls":[],"fragment_urls":[],"princeton_url":"https://geniza.princeton.edu/documents/28975/","mentioned":"","description_he":"תיאורי תכולת אוסף ספרים בשני כתבי יד שונים: הראשון, מסודר יותר, מזכיר יהודה ב' יחיא וטקסט ה'תאג'' ובראשית רבה והתורה וחמש המגילות ובאר היטב וגמרא חולין והלכות שחיטה. הבלוק השני בכתב יד גולמי קשה יותר לקריאה, מזכיר: עין יעקב, פסיקתא הנשיא הגדול, חומש הגדול ורב אלפס ו'שלושה קטעים מהרמב\"ם'. חותם 'אני מנ[ח?]ם ב' יהודה אל-מוג'הד (?)'. ככל הנראה מאוחר, לפחות מהמאה ה-16.","prev":"28974","next":"28976","pos":28395,"total":35924}