{"id":"29250","shelfmark":"T-S 16.139","multifragment":"","type_en":"Letter","type_he":"מכתב","lang_en":"Aramaic, Hebrew, Judaeo-Arabic","lang_he":"Aramaic, Hebrew, Judaeo-Arabic","lang2_en":"","lang2_he":"","lang_note":"Hebrew (isolated Tiberian vocalisation)","origin":"","destination":"","region":"","date":"","date_original":"","date_standard":"","date_inferred":"","date_rationale":"","library":"ספריית קיימברידג'","library_raw":"CUL","collection":"CUL, T-S","description":"Recto: poetic letter in square script. Each line ends in the rhyme -let and is followed by a dot. Letters are extended to give a (mostly) neat left-hand margin. The final word of the last line is put in the middle of the page. No names preserved, but does address אדוני. Worman states that it was ‘sent by a son of Yehoshuaʿ the Ḥaver to Yehoshuaʿ’s brother’, but there is no trace of this in the fragment now. Verso: collection of halakhic rulings regarding marriage, which continues in the blank space under the letter on recto, overwriting the final word. (Information from CUDL)","tags":[],"has_transcription":false,"has_translation":false,"iiif_urls":["https://cudl.lib.cam.ac.uk/iiif/MS-TS-00016-00139"],"fragment_urls":["https://cudl.lib.cam.ac.uk/view/MS-TS-00016-00139"],"princeton_url":"https://geniza.princeton.edu/documents/29250/","mentioned":"","description_he":"רקטו: מכתב פיוטי בכתב מרובע. כל שורה מסתיימת בחרוז -לת ואחריה נקודה. האותיות מוארכות ליצירת שוליים שמאליים סדורים. המילה האחרונה של השורה האחרונה ממוקמת באמצע העמוד. אין שמות שמורים, אך פונה לאדוני. ורסו: אוסף פסיקות הלכתיות בנושא נישואים, הממשיך במרחב הפנוי מתחת למכתב ברקטו.","prev":"29249","next":"29252","pos":16697,"total":35924}