{"id":"30525","shelfmark":"AIU VII.D.26","multifragment":"","type_en":"Legal document","type_he":"מסמך משפטי","lang_en":"Aramaic, Hebrew","lang_he":"Aramaic, Hebrew","lang2_en":"","lang2_he":"","lang_note":"","origin":"","destination":"","region":"","date":"1799-12-13","date_original":"15 Kislev 5560","date_standard":"1799-12-13","date_inferred":"","date_rationale":"","library":"כיא פריז","library_raw":"AIU","collection":"AIU","description":"Ketubba dated 13 December 1799 CE (15 Kislev 5560 AM) from Cairo, for Yiṣḥaq b. Avraham Muḥibb and Palomba bt. Shalom ha-Levi. The me'ukhar is 20,000 muayyadis of silver. The right and middle signatures were recorded by the scribe Meir Ben-Naʿim, who also signed on behalf of the groom. The signature on the left is Yaʿaqov Yuʿbaṣ.","tags":["Ben Na'im, ketubba, 18th c, muayyadi, Yu'bas"],"has_transcription":false,"has_translation":false,"iiif_urls":[],"fragment_urls":[],"princeton_url":"https://geniza.princeton.edu/documents/30525/","mentioned":"","description_he":"כתובה מתוארכת 13 בדצמבר 1799 (ט\"ו כסלו ה'תק\"ס) מקהיר, ליצחק בן אברהם מחיב ולפלומבה בת שלום הלוי. המאוחר 20,000 מואיידי כסף. הסופר מאיר בן נעים חתם גם בשם החתן. החתימה השמאלית היא יעקב יועבץ.","tags_he":["מסמך משפטי","כתובה","קהיר"],"prev":"30524","next":"30526","pos":28763,"total":35924}