{"id":"32529","shelfmark":"T-S Ar.34.159","multifragment":"","type_en":"List or table","type_he":"רשימה או טבלה","lang_en":"Judaeo-Arabic","lang_he":"יהודית-ערבית","lang2_en":"","lang2_he":"","lang_note":"","origin":"","destination":"","region":"","date":"","date_original":"","date_standard":"","date_inferred":"","date_rationale":"","library":"ספריית קיימברידג'","library_raw":"CUL","collection":"CUL, T-S","description":"Accounts in Judaeo-Arabic. Dating: 11th or 12th century. The hand is probably known. The goods include rose water and cloves.","tags":[],"has_transcription":false,"has_translation":false,"iiif_urls":[],"fragment_urls":[],"princeton_url":"https://geniza.princeton.edu/documents/32529/","mentioned":"","description_he":"חשבונות בערבית-יהודית. תיארוך: מאה ה-11 או ה-12. כתב היד כנראה מוכר. הסחורות כוללות מי ורדים וציפורן.","prev":"32528","next":"32530","pos":30173,"total":35924}