{"id":"34200","shelfmark":"T-S 8J16.19 + T-S NS 323.13","multifragment":"","type_en":"List or table","type_he":"רשימה או טבלה","lang_en":"Arabic","lang_he":"ערבית","lang2_en":"","lang2_he":"","lang_note":"","origin":"","destination":"","region":"b ; b","date":"","date_original":"","date_standard":"","date_inferred":"","date_rationale":"","library":"ספריית קיימברידג' · ספריית קיימברידג'","library_raw":"CUL ; CUL","collection":"CUL, T-S ; CUL, T-S","description":"Accounts in Arabic script and Greek/Coptic numerals. \"sharḥ mā taḥaṣṣala min thamn al-[...].\" This seems to be the third reuse of the fragment: first it was a decree, then it was a letter, then it was torn and used for accounts (note that the accounts constitute the only document that is not continuous across the tear). Several names appear, including Bishr al-ʿAṭṭār.","tags":[],"has_transcription":false,"has_translation":false,"iiif_urls":["https://cudl.lib.cam.ac.uk/iiif/MS-TS-00008-J-00016-00019","https://cudl.lib.cam.ac.uk/iiif/MS-TS-NS-00323-00013"],"fragment_urls":["https://cudl.lib.cam.ac.uk/view/MS-TS-00008-J-00016-00019/1","https://cudl.lib.cam.ac.uk/view/MS-TS-NS-00323-00013/1"],"princeton_url":"https://geniza.princeton.edu/documents/34200/","mentioned":"","description_he":"חשבונות בכתב ערבי ובספרות יווניות/קופטיות. 'שרח מא תחצל מן ת'מן אל[...].' נראה שזהו השימוש השלישי בקטע: תחילה צו, אחר כך מכתב, ואחר כך נקרע ושימש לחשבונות. מופיעים שמות שונים, כולל בשר אלעטאר.","prev":"34199","next":"34201","pos":18549,"total":35924}