{"id":"34793","shelfmark":"MIAC 27","multifragment":"","type_en":"Letter","type_he":"מכתב","lang_en":"Arabic","lang_he":"ערבית","lang2_en":"","lang2_he":"","lang_note":"","origin":"","destination":"","region":"","date":"1935-05-03","date_original":"1935","date_standard":"1935-05-03","date_inferred":"","date_rationale":"","library":"ENL","library_raw":"ENL","collection":"ENL, ENL 'New Geniza' Catalogue","description":"Announcement from the Grand Rabbinate of Cairo [Ḥakhamhāne Miṣr] for the celebration of the coronation of the King of Britain – Museum of Islamic Art – 3 May 1935CE – (number 27) – in Arabic. (information from Ḥassanein Muḥammad Rabīʿa, ed., Dalīl Wathā'iq al-Janīza al-Jadīda / Catalogue of the Documents of the New Geniza, 57). No British monarch was coronated in this year, however, the Silver Jubilee of King George V was celebrated three days after this announcement on May 6 1935CE. A scan of this document that is mostly legible can be found in Al-Janiza wa-l-maʿābid al-Yahūdiyya fī Miṣr (p.170) where Ḥasan and Sarrāj analyze its contents and mention that the document came from the Mosseri family crypt at the Bassatine Cemetery during an excavation in 1987. This analysis also cites the venue of the celebration mentioned in the communal announcement: the Ismaʿilīya Synagogue on ʿAdlī Street in Cairo. MCD.","tags":["Mosseri, British, late synagogues, 20th c"],"has_transcription":false,"has_translation":false,"iiif_urls":[],"fragment_urls":[],"princeton_url":"https://geniza.princeton.edu/documents/34793/","mentioned":"","description_he":"מכתב בערבית. מוחזק בENL.","prev":"34792","next":"34796","pos":31016,"total":35924}