{"id":"34880","shelfmark":"T-S K22.27","multifragment":"","type_en":"Legal document","type_he":"מסמך משפטי","lang_en":"Hebrew","lang_he":"עברית","lang2_en":"","lang2_he":"","lang_note":"","origin":"","destination":"","region":"","date":"1693","date_original":"","date_standard":"1693","date_inferred":"","date_rationale":"","library":"ספריית קיימברידג'","library_raw":"CUL","collection":"CUL, T-S","description":"Legal record (#8) in a court register/pinqas from a beit din in Cairo (on f. 1r of T-S K22.27). In Hebrew. Location: Cairo. Undated, neighboring entries are circa 1693 CE. The first seven entries are counted within the potential join K25.140.2 (PGPID 40947).\n\n(Document #8) The final lines of a dowry list with various types of gold jewelry. Neither the bride's nor groom's names are preserved. It is possible this entry comprises the final lines of Document #13 in the same court register (PGPID 40952). MCD.","tags":[],"has_transcription":false,"has_translation":false,"iiif_urls":[],"fragment_urls":[],"princeton_url":"https://geniza.princeton.edu/documents/34880/","mentioned":"","description_he":"פרוטוקול בית דין (#8) מתוך פנקס בית הדין בקהיר (T-S K22.27 דף 1r). בעברית. קהיר, כ-1693 לסה'נ. סוף רשימת נדוניה עם תכשיטי זהב שונים; שמות החתן והכלה לא שמורים. ייתכן שמהווה את הסיום של פרוטוקול #13 באותו פנקס.","tags_he":["מסמך משפטי","עברית","נדוניה","פרוטוקול בית דין","קהיר"],"prev":"34878","next":"34881","pos":31090,"total":35924}