{"id":"36659","shelfmark":"Moss. II,147.3","multifragment":"","type_en":"Letter","type_he":"מכתב","lang_en":"Judaeo-Arabic","lang_he":"יהודית-ערבית","lang2_en":"","lang2_he":"","lang_note":"","origin":"","destination":"","region":"","date":"","date_original":"","date_standard":"","date_inferred":"","date_rationale":"","library":"אוסף מוסרי","library_raw":"Mosseri","collection":"Mosseri, Moss.","description":"Letter fragment (lower right corner). In Judaeo-Arabic. Mentions Sayyidnā twice, swears by Jerusalem, and mentions the unit of currency rubāʿī.","tags":[],"has_transcription":false,"has_translation":false,"iiif_urls":[],"fragment_urls":[],"princeton_url":"https://geniza.princeton.edu/documents/36659/","mentioned":"","description_he":"שבר מכתב (פינה תחתונה ימנית). בערבית-יהודית. מזכיר את 'סיידנא' פעמיים, נשבע בירושלים, ומזכיר את יחידת המטבע רובאעי.","tags_he":["מכתב","יהודית-ערבית","נישואין","ירושלים"],"prev":"36658","next":"36660","pos":32220,"total":35924}