{"id":"37653","shelfmark":"Moss. IXa,2.3","multifragment":"","type_en":"Letter","type_he":"מכתב","lang_en":"Arabic","lang_he":"ערבית","lang2_en":"","lang2_he":"","lang_note":"","origin":"","destination":"","region":"","date":"","date_original":"","date_standard":"","date_inferred":"","date_rationale":"","library":"אוסף מוסרי","library_raw":"Mosseri","collection":"Mosseri, Moss.","description":"Possibly a letter (on verso: يا سيدي). But shape, layout and recto-verso similiarity suggest it may be a literary text. Washed and damaged, difficult to read.","tags":["DIMME"],"has_transcription":false,"has_translation":false,"iiif_urls":[],"fragment_urls":[],"princeton_url":"https://geniza.princeton.edu/documents/37653/","mentioned":"","description_he":"אולי מכתב (בורסו: יא סיידי). אך הצורה, הפריסה והדמיון בין הרקטו לורסו מרמזים שאולי מדובר בטקסט ספרותי. שטוף ופגום, קשה לקריאה.","prev":"37652","next":"37654","pos":33171,"total":35924}