{"id":"37938","shelfmark":"L-G Ar. I.97","multifragment":"","type_en":"State document","type_he":"מסמך ממלכתי","lang_en":"Arabic","lang_he":"ערבית","lang2_en":"Greek/Coptic Numerals","lang2_he":"Greek/Coptic Numerals","lang_note":"","origin":"","destination":"","region":"","date":"","date_original":"","date_standard":"","date_inferred":"","date_rationale":"","library":"CUL & Bodl.","library_raw":"CUL & Bodl.","collection":"CUL & Bodl., L-G","description":"State document, draft of a report, in Arabic script. Addressed to a lower official whose titles are \"al-Rayyis al-Muḥrim al-Amīr ʿImād al-Mulk\". Reports an event occurred on the bank of the Nile or the sea (shāṭiʾ l-baḥr). Dating: probably 13th century. Coptic/Greek numerals interspersed between l7, l9 and margin, probably from later reuse for accounts on verso (see different entry).","tags":["DIMME"],"has_transcription":false,"has_translation":false,"iiif_urls":[],"fragment_urls":[],"princeton_url":"https://geniza.princeton.edu/documents/37938/","mentioned":"","description_he":"מסמך ממלכתי בערבית. מוחזק בCUL & Bodl..","prev":"37935","next":"37939","pos":33418,"total":35924}