{"id":"39125","shelfmark":"T-S Ar.54.19","multifragment":"","type_en":"Letter","type_he":"מכתב","lang_en":"Judaeo-Arabic","lang_he":"יהודית-ערבית","lang2_en":"","lang2_he":"","lang_note":"","origin":"","destination":"","region":"","date":"","date_original":"","date_standard":"","date_inferred":"","date_rationale":"","library":"ספריית קיימברידג'","library_raw":"CUL","collection":"CUL, T-S","description":"Fol. 10r: Letter fragment. In Judaeo-Arabic. The first few lines and the upper margin are preserved. Muslim/Musallam sends his regards. Almost all the content preserved is formulaic.","tags":["IB5, India"],"has_transcription":false,"has_translation":false,"iiif_urls":["https://cudl.lib.cam.ac.uk/iiif/MS-TS-AR-00054-00019"],"fragment_urls":["https://cudl.lib.cam.ac.uk/view/MS-TS-AR-00054-00019"],"princeton_url":"https://geniza.princeton.edu/documents/39125/","mentioned":"","description_he":"מכתב ביהודית-ערבית. מוחזק בספריית קיימברידג'.","prev":"39124","next":"39126","pos":19782,"total":35924}