{"id":"40300","shelfmark":"JRL B 8455","multifragment":"","type_en":"Letter","type_he":"מכתב","lang_en":"Judaeo-Arabic","lang_he":"יהודית-ערבית","lang2_en":"","lang2_he":"","lang_note":"","origin":"","destination":"","region":"","date":"","date_original":"","date_standard":"","date_inferred":"","date_rationale":"","library":"JRL","library_raw":"JRL","collection":"JRL","description":"Letter fragment in Judaeo-Arabic. Refers to something gilded (mudhahhaba) weighing a certain amount; later again refers to gold; concludes with expressions of deference and possibly requesting that the addressee help somebody.","tags":[],"has_transcription":false,"has_translation":false,"iiif_urls":[],"fragment_urls":[],"princeton_url":"https://geniza.princeton.edu/documents/40300/","mentioned":"","description_he":"קטע מכתב ביהודית-ערבית, מתייחס לחפץ מוזהב במשקל מסוים ולזהב, ומסתיים בביטויי כבוד ובקשת עזרה","tags_he":["מכתב","יהודית-ערבית"],"prev":"40299","next":"40302","pos":34929,"total":35924}