{"id":"40617","shelfmark":"ENA NS 37.7","multifragment":"","type_en":"Letter","type_he":"מכתב","lang_en":"Hebrew","lang_he":"עברית","lang2_en":"","lang2_he":"","lang_note":"","origin":"","destination":"","region":"","date":"","date_original":"","date_standard":"","date_inferred":"","date_rationale":"","library":"בית המדרש לרבנים","library_raw":"JTS","collection":"JTS","description":"Letter in Hebrew mentioning payments in gold peraḥīm coinage. Dated 24 Nissan below the main section of text, possibly with a two-alphanumeral year. The latter part of the date is unclear in meaning, but likely falls in the 15th- or 16th-century based on the paleography.","tags":["cmp, 15th or 16th c"],"has_transcription":false,"has_translation":false,"iiif_urls":["https://figgy.princeton.edu/concern/scanned_resources/f5684036-822b-49ae-ba87-d23bd3bec050/manifest"],"fragment_urls":[],"princeton_url":"https://geniza.princeton.edu/documents/40617/","mentioned":"","description_he":"מכתב בעברית המזכיר תשלומים במטבע פרחים זהב; מתוארך 24 בניסן, כנראה מהמאה ה-15 או 16","tags_he":["מכתב","עברית"],"prev":"40616","next":"40618","pos":20277,"total":35924}