{"id":"41590","shelfmark":"UPenn RAR MS 85.126.18b","multifragment":"","type_en":"List or table","type_he":"רשימה או טבלה","lang_en":"Greek/Coptic Numerals, Judaeo-Arabic","lang_he":"Greek/Coptic Numerals, Judaeo-Arabic","lang2_en":"Arabic","lang2_he":"ערבית","lang_note":"","origin":"","destination":"","region":"","date":"","date_original":"","date_standard":"","date_inferred":"","date_rationale":"","library":"Penn","library_raw":"Penn","collection":"Penn","description":"Accounts mainly in Judaeo-Arabic and Greek/Coptic numerals, with some Arabic script. Dating: the handwriting looks ca. 13th or 14th century. Items include saffron, cinnamon, wax, kohl, collyria (ashyāf), vinegar, rope, kaʿk, a donkey, a qāṣid (guide), duck, rice, date, onion, waste disposal, and bread.","tags":[],"has_transcription":false,"has_translation":false,"iiif_urls":[],"fragment_urls":[],"princeton_url":"https://geniza.princeton.edu/documents/41590/","mentioned":"","description_he":"חשבונות בעיקר ביהודית-ערבית ובספרות יווניות/קופטיות, עם כמה בכתב ערבי. תיארוך: כתב היד נראה כ-המאה ה-13 או ה-14. הפריטים כוללים זעפרן, קינמון, שעווה, כחל, קולירייה (אשיאף), חומץ, חבל, כעכ, חמור, קאצד (מדריך), ברווז, אורז, תמר, בצל, פינוי פסולת ולחם.","tags_he":["חשבונות"],"prev":"41589","next":"41591","pos":35868,"total":35924}