{"id":"5838","shelfmark":"T-S 12.2","multifragment":"","type_en":"Letter","type_he":"מכתב","lang_en":"Judaeo-Arabic","lang_he":"יהודית-ערבית","lang2_en":"","lang2_he":"","lang_note":"","origin":"Qayrawān","destination":"Fustat","region":"","date":"Ca. 1045","date_original":"","date_standard":"","date_inferred":"Ca. 1045","date_rationale":"Other (please specify)","library":"ספריית קיימברידג'","library_raw":"CUL","collection":"CUL, T-S","description":"Letter from Yosef b. Yaʿaqov b. Yahboy, probably in Qayrawān, to an unknown addressee, in Fustat. Dating: ca. 1045 according to Gil. The writer is sorting out the affairs of a deceased trader named Abū ʿImrān Mūsā b. Netanʾel, and trying to recover money owed to him. The letter refers to the towns of Ṣafāqis (Sfax) and al-Mahdiyya in Tunisia; and Alexandria, Fusṭāṭ, and Ashmūnayn in Egypt. Many names are mentioned: Abū ʿImrān Mūsā b. Yiṣḥaq, Ibn al-Qumuddī, Nahray b. Nissim, Abū Naṣr Dāʾūd who is to serve as a witness along with the addressee), Abū l-Surūr Yūshaʿ b. Natan (appointed by the sender as his agent/wakīl), and Abū l-Faraj b. ʿAllān (who is asked to give a suftaja on his assets in al-Ushmūnayn and to let his representatives there, the Banī l-Baradānī, collect). (Information from CUDL, Goitein's index card, and Gil, Kingdom, Vol. 4, #732) VMR","tags":["suftaja"],"has_transcription":false,"has_translation":false,"iiif_urls":["https://cudl.lib.cam.ac.uk//iiif/MS-TS-00012-00002"],"fragment_urls":["https://cudl.lib.cam.ac.uk/view/MS-TS-00012-00002/1"],"princeton_url":"https://geniza.princeton.edu/documents/5838/","mentioned":"Alexandria, Sfax, al-Mahdiyya, al-Ushmūnayn","description_he":"מכתב מיוסף בן יעקב בן יחבוי, כנראה בקיירואן, לנמען אנונימי, פוסטאט, כ-1045, על הסדרת ענייני סוחר שנפטר","prev":"5835","next":"5839","pos":3826,"total":35924}