{"id":"6405","shelfmark":"Bodl. MS heb. c 13/2","multifragment":"","type_en":"Paraliterary text","type_he":"טקסט פרא-ספרותי","lang_en":"Arabic","lang_he":"ערבית","lang2_en":"","lang2_he":"","lang_note":"","origin":"","destination":"","region":"","date":"","date_original":"","date_standard":"","date_inferred":"","date_rationale":"","library":"בודליאן אוקספורד","library_raw":"Bodl.","collection":"Bodl.","description":"Magical text. Six pages, Arabic script. See also Bodl. MS heb. c 13/3 (PGPID 6406). (Information from Goitein’s index card)","tags":[],"has_transcription":false,"has_translation":false,"iiif_urls":["https://princetongenizalab.github.io/iiif/bodleian/c/ms-heb-c-13-2.json"],"fragment_urls":["https://genizah.bodleian.ox.ac.uk/catalog/volume_25#MS_Heb_c_13-part2"],"princeton_url":"https://geniza.princeton.edu/documents/6405/","mentioned":"","description_he":"טקסט כישוף; שישה עמודים, בכתב ערבי","prev":"6404","next":"6406","pos":4132,"total":35924}