{"id":"663","shelfmark":"ENA 2592.15","multifragment":"","type_en":"Legal query or responsum","type_he":"Legal query or responsum","lang_en":"Hebrew","lang_he":"עברית","lang2_en":"","lang2_he":"","lang_note":"","origin":"","destination":"","region":"","date":"","date_original":"","date_standard":"","date_inferred":"","date_rationale":"","library":"JTS","collection":"JTS","description":"Responsum of Daniel b. Azarya about a dispute between men named Avraham and Yaʿaqov.","tags":["Responsum"],"has_transcription":false,"has_translation":false,"iiif_urls":["https://figgy.princeton.edu/concern/scanned_resources/21af9458-0cd6-4ba3-b711-aa68b182779b/manifest"],"fragment_urls":[],"princeton_url":"https://geniza.princeton.edu/documents/663/","mentioned":"","prev":"662","next":"664","pos":128,"total":500}