{"id":"8208","shelfmark":"T-S Ar.38.20","multifragment":"","type_en":"Paraliterary text","type_he":"טקסט פרא-ספרותי","lang_en":"Hebrew","lang_he":"עברית","lang2_en":"","lang2_he":"","lang_note":"","origin":"","destination":"","region":"","date":"","date_original":"","date_standard":"","date_inferred":"","date_rationale":"","library":"ספריית קיימברידג'","library_raw":"CUL","collection":"CUL, T-S","description":"Verso: Poem for a circumcision (ולמצוץ כדת...). It seems for the son of the Nagid Mevorakh (gaʾon ʿam ve-sar sarim). (Information from Goitein's index card.)","tags":[],"has_transcription":false,"has_translation":false,"iiif_urls":[],"fragment_urls":[],"princeton_url":"https://geniza.princeton.edu/documents/8208/","mentioned":"","description_he":"גב: שיר לרגל ברית מילה. נראה לבנו של הנגיד מבורך","prev":"8205","next":"8211","pos":21294,"total":35924}